{"isWplusMember":false,"viscosity":null,"showSubscriptionModule":false,"fulfillmentTitle":"title_shipToHome_date_free_delivery","gender":"Unisex","petRxEligible":null,"brand":"Cricut","id":"4D7UTK8BDODY","fulfillmentTypeClassification":null,"model":"zJoyM6","buyBoxSuppression":false,"eventAttributes":{"priceFlip":false,"specialBuy":false},"transactableOfferCount":2,"snapEligible":false,"personalizable":false,"weightIncrement":1,"showAddOnServices":true,"tireSize":null,"experienceType":null,"brandUrl":"/c/brand/cricut","secondaryOfferPrice":{"currentPrice":{"price":174.99,"priceString":"$174.99","priceType":null}},"showFulfillmentLink":false,"wfsEnabled":false,"preOrder":{"isPreOrder":false},"additionalOfferCount":1,"category":{"categoryPathId":"0:1334134:9799587:7470587","path":[{"name":"Arts Crafts & Sewing","url":"/cp/arts-crafts-sewing/1334134"},{"name":"Cricut","url":"/cp/cricut/9799587"},{"name":"Cricut Machines","url":"/cp/cricut-machines/7470587"}]},"langUrls":null,"type":"Die-Cut Machines","selectedVariantIds":[],"sellerDisplayName":"Craft-e-Corner","ebooks":null,"maxRewardAmongAllVariants":null,"subscription":{"showSubscriptionModule":false,"subscriptionEligible":false,"subscriptionSubmessage":"NONE","subscriptionTransactable":false},"fulfillmentSummary":[{"calculatedSlaDays":7,"deliveryDate":"2023-12-22T20:00:00.000Z","fulfillment":"DELIVERY","fulfillmentBadge":null,"fulfillmentMethods":["UNSCHEDULED"],"isFreeForWPlus":null,"sla":{"measurementValue":7,"unitOfMeasure":"DAY"},"storeId":"0"}],"offerType":"ONLINE_ONLY","returnPolicy":{"freeReturns":true,"holidayReturnEnabled":false,"returnPolicyCondition":null,"returnPolicyText":"Free 90-day returns","returnWindow":{"unitType":"Day","value":90},"returnable":true},"shortDescription":"Quick, personalized greeting cards with big impact are at your fingertips! Cut intricate and meaningful words and images into the face of the card to let the beautiful insert color show through. <br>Step away from your inspiration boards and turn your best intentions into action with a little help from Cricut Joy, your DIY best friend. This smart little cutting and writing machine is ridiculously easy to set up and use, so you'll find endless excuses to personalize, organize, and customize every single day. Cut custom vinyl decals for water bottles or your wall. Make labels for your kitchen or office. Bust out a custom card or a birthday banner. It's also compatible with Cricut Smart Materials, for super-easy, super-long cuts without a cutting mat. Just load & go! With plenty of projects that take just 15 minutes, Cricut Joy makes it possible to make something unique for you or anyone  at a moment's notice. <br> <br>Features: <br> <br>-Weighing in at only 3.9 lbs (1.75 kg), this smart little cutting and writing machine makes it easy to personalize almost anything <br>-Cuts 50+ materials, including iron-on, cardstock, vinyl, paper, and Smart Materials super-easy, super-long cuts without a cutting mat <br>-Draws any shape and writes in a variety of style <br>-Cuts individual shapes up to 4 ft long or makes repeated cuts up to 20 ft long<br>-Bluetooth wireless technology<br>-Design Space software for iOS, Android, Windows, and Mac<br><br>INCLUDED<br>-Cricut Joy Machine<br>-Blade + Housing<br>-Fine Point Pen, Black (0.4mm)<br>-StandardGrip Mat, 4.5 x 6.5<br>-Welcome Card<br>-Power Adapter<br>-Materials for a practice cut<br>-50 Ready-to-Make Projects Online<br><br>BUNDLED WITH<br>-Cricut Joy Insert Cards - Sampler Set (Colors May Vary)<br>-Cricut Joy Card Mat, 4.5 x 6.25<br>-Cricut Joy Gel Pens 3ct (Colors May Vary)","usItemId":"208591424","offerId":"9B6E216CBC5F47328AAC482FE1663764","fulfillmentBadge":null,"checkAvailabilityGlobalDFS":false,"variantProductIdMap":{},"orderMinLimit":1,"discounts":null,"displayOfferLevelImage":null,"sellerAverageRating":4.2639,"preownedCondition":null,"tireSpeedRating":null,"fsaEligibleInd":false,"externalInfo":null,"subscriptionEligible":false,"wfsProviderName":null,"suppressReviews":false,"pickupOption":{"accessTypes":[],"availabilityStatus":null,"slaTier":null,"storeId":null,"storeName":null},"rhPath":"20000:22000:22001:22105:22232","variantCriteria":[],"classType":"REGULAR","annualEvent":false,"itemType":null,"sellerName":"Duehring Enterprises LLC","priceInfo":{"capType":1,"comparisonPrice":null,"currentPrice":{"bestValue":null,"currencyUnit":"USD","price":149.99,"priceDisplay":"Now $149.99","priceString":"$149.99","variantPriceString":"$149.99"},"isPriceReduced":true,"listPrice":null,"priceDisplayCodes":{"clearance":null,"eligibleForAssociateDiscount":null,"finalCostByWeight":null,"priceDisplayCondition":null,"reducedPrice":null,"rollback":null,"submapType":null},"priceRange":{"currencyUnit":null,"denominations":null,"maxPrice":null,"minPrice":null,"priceString":null},"priceReducedDisplay":"Now $149.99","savings":null,"savingsAmount":{"amount":90.36,"priceString":"SAVE $90.36"},"secondaryOfferBoost":null,"shipPrice":null,"subscriptionPrice":null,"unitPrice":null,"wPlusEarlyAccessPrice":null,"walmartFundedAmount":null,"wasPrice":{"bestValue":null,"currencyUnit":"USD","price":240.35,"priceString":"$240.35","variantPriceString":null}},"productTypeId":"2724","vision":{"ageGroup":"Adult","visionCenterApproved":false},"motorOilType":null,"location":{"addressId":null,"city":"Lake Worth","intent":"SHIPPING","mpPickupLocation":null,"pickupLocation":{"accessPointId":null,"accessType":null,"storeId":"1398"},"postalCode":"33467","stateOrProvinceCode":"FL","storeIds":["1398"]},"earlyAccessEvent":false,"addOnServices":[{"groups":[{"assetUrl":"https://i5.walmartimages.com/seo/2-Year-Protection-Plan-For-Crafts-100-199-99_b04b2969-4200-4781-9f3a-3da0ccca5d4d.06e6f536cfdbec82e8b0108a6488901d.jpeg","groupTitle":"Walmart Protection Plan by Allstate","groupType":"WPP","nearByStores":null,"services":[{"currentPrice":{"price":16,"priceString":"$16.00"},"displayName":"2-Year plan - $16.00","giftEligible":true,"name":"2-Year","offerId":"4F496E6CEEFF498D8363F61D1E9DC244","selectedDisplayName":"Walmart Protection Plan by Allstate - 2-Year","serviceMetaData":null,"usItemId":"314321652"},{"currentPrice":{"price":22,"priceString":"$22.00"},"displayName":"3-Year plan - $22.00","giftEligible":true,"name":"3-Year","offerId":"03386F9DC08E495A87E803679E943876","selectedDisplayName":"Walmart Protection Plan by Allstate - 3-Year","serviceMetaData":null,"usItemId":"909871957"}],"shortDescription":"<p>Get years of protection for just pennies a day.</p><p><b>Plan covers:</b></p><ul><li>Mechanical & Electrical Failures</li><li>Item Failures During Normal Use, or from Normal Wear & Tear</li><li>Other Common Malfunctions</li></ul><p><b>Plan includes:</b></p><ul><li>24/7 Customer Support</li><li>Easy Online Claims</li><li>Fast Repairs or Replacements</li></ul><p><b>Protect it today. Enjoy it for years.</b></p><p>Simply add a Walmart Protection Plan to your order and checkout as usual. There is no need to register your plan for it to be active. We’ll send plan details to your email address after purchase.</p><p><b>Award-winning protection backed by Allstate</b></p><p>Allstate has been protecting people and the things they love most for over 85 years. So you know your purchase is in good hands.</p>","unavailabilityReason":null}],"serviceSubTitle":"Get the best value on product protection including fast repairs or replacements.","serviceTitle":"Protect your purchase","serviceType":"CAREPLAN"}],"availabilityInNearbyStore":null,"sellerReviewCount":379,"aaiaBrandId":null,"primaryUsItemId":null,"classId":"1","manufacturerProductId":"zJoyM6","showBuyWithWplus":false,"hasCarePlans":true,"isEarlyAccessItem":false,"ozarkAttributes":{"exactAddress":false,"shippingPromise":null},"fulfillmentLabel":[{"addressEligibility":true,"checkStoreAvailability":null,"fulfillmentMethod":"SHIPPING","fulfillmentText":"arrives by Fri, Dec 22","fulfillmentType":"MARKETPLACE","locationText":"Lake Worth, 33467","message":"Free shipping, arrives by Fri, Dec 22 to Lake Worth, 33467","postalCode":"33467","shippingText":"Free shipping","wPlusFulfillmentText":null}],"sellerType":"EXTERNAL","zeekitData":null,"variantsMap":{},"giftingEligibility":false,"shippingOption":{"availabilityStatus":"AVAILABLE","deliveryDate":"2023-12-22T20:00:00.000Z","internationalShipping":null,"maxDeliveryDate":null,"shipMethod":"STANDARD","shipPrice":{"bestValue":null,"currencyUnit":null,"price":0,"priceString":"$0.00","variantPriceString":null},"slaTier":"THREE_TO_FIVE_DAY"},"legalRestriction":false,"ironbankCategory":"Art & Craft","catalogSellerId":432,"salesUnit":"EACH","fulfillmentType":"MARKETPLACE","petRx":{"eligible":false,"singleDispense":null},"averageRating":4.4,"pac":null,"badges":{"flags":null,"groups":[],"labels":null,"tags":[]},"showExploreOtherConditionsCTA":false,"variants":[],"hasHomeServices":null,"promoData":[{"description":"pay <b>$15/mo</b> with <img src=\"https://cdn-assets.affirm.com/images/black_logo-white_bg.jpg\" alt=\"Affirm\">","id":"cf02bb05-5d2e-448d-b00a-61c16fc8b033","installmentsPromotion":null,"noInterestInstallmentsPromotion":null,"templateData":{"aprString":null,"financeDataPromotionType":"interest","imageUrl":"https://cdn-assets.affirm.com/images/black_logo-white_bg.jpg","priceString":"$15/mo"},"terms":"https://www.affirm.com/walmart/learn?referring_url=https%3A%2F%2Fwww.walmart.com&unit_price=14999&interest_rate=2160&apr=2197&term_length=12&monthly_payment=1500&monthly_payment_exact=1404&promo_name=12r","type":"Affirm"}],"conditionType":null,"imageInfo":{"allImages":[{"id":"9068DF2E202A4C2D86B21D850B4E45FC","url":"https://i5.walmartimages.com/seo/Cricut-Joy-Machine-DIY-Card-Making-Bundle-Sampler-Insert-Cards-Mat-Gel-Pens_8ac4f379-ab6c-4ccf-930c-856a6dcedf00.e4669163d45ac5aa7243ba8a417d4a08.jpeg","zoomable":true},{"id":"C2149D37E917408A88F86150F39EE879","url":"https://i5.walmartimages.com/asr/eebf3dd8-6783-4730-8df3-9790d4e7ef46.b84e66281c81aa307464cf8fd93dd3e4.jpeg","zoomable":true},{"id":"F234948CE76E414FBB091AA7DC05E479","url":"https://i5.walmartimages.com/asr/6ce6c7d7-741a-45a8-ae2f-41d038272812.1ad28b9904bcaf72216ba582333bbf79.jpeg","zoomable":true},{"id":"03388998CEA04C3C942AADFCE8A4571A","url":"https://i5.walmartimages.com/asr/7b90beea-4bf8-4252-9b53-117778212dc0.89a41b568706adc69fa41f442859cc0c.jpeg","zoomable":true},{"id":"D10C5AD479B44A088AF683646B77A6EA","url":"https://i5.walmartimages.com/asr/834886ae-c046-46ca-94e1-4a4f68c82062.5931115d359bb7ec0dfc1c17ed7c8428.jpeg","zoomable":true},{"id":"D3D1D282176C4284BF4D9D32C07A7149","url":"https://i5.walmartimages.com/asr/e462fb0c-f2df-4697-a8de-31d91d4a53ed.6316edda02731c7c4eb631808d62aa6a.jpeg","zoomable":true},{"id":"41F99BCE99994795B04DEBDFFE992603","url":"https://i5.walmartimages.com/asr/e688b3c3-328a-448f-af83-db2ec06c2aa4.ea0f7f312f8d0dff4ccd5333c9987f1c.jpeg","zoomable":true}],"thumbnailUrl":"https://i5.walmartimages.com/seo/Cricut-Joy-Machine-DIY-Card-Making-Bundle-Sampler-Insert-Cards-Mat-Gel-Pens_8ac4f379-ab6c-4ccf-930c-856a6dcedf00.e4669163d45ac5aa7243ba8a417d4a08.jpeg"},"tireLoadIndex":null,"productLocation":null,"checkStoreAvailabilityATC":false,"hasSellerBadge":true,"imageMap":{},"newConditionProductId":null,"upc":"037182176957","redirect":{"replacedByItemId":"","replacedByProductId":"","replacedByProductUrlText":""},"shippingRestriction":false,"availabilityStatus":"IN_STOCK","blitzItem":null,"promoDiscount":null,"rewards":null,"associatedBundleId":null,"orderLimit":12,"numberOfReviews":25,"isPreowned":false,"buyNowEligible":true,"semStoreData":null,"canonicalUrl":"/ip/Cricut-Joy-Machine-DIY-Card-Making-Bundle-Sampler-Insert-Cards-Mat-Gel-Pens/208591424","groupMetaData":null,"name":"Cricut Joy Machine DIY Card Making Bundle - Sampler Insert Cards, Mat, Gel Pens","fulfillmentOptions":[{"__typename":"ShippingOptionV2","availabilityStatus":"IN_STOCK","availableQuantity":817,"intent":true,"inventoryStatus":null,"locationText":"Lake Worth, 33467","maxOrderQuantity":12,"orderLimit":12,"restricted":false,"selected":false,"speedDetails":{"deliveryDate":"2023-12-22T20:00:00.000Z","freeFulfillment":true,"fulfillmentBadge":null,"fulfillmentPrice":null,"wPlusEligible":false},"subscriptionSubmessage":"NONE","type":"SHIPPING"},{"__typename":"PickupOptionV2","availabilityStatus":"NOT_AVAILABLE","availableQuantity":null,"checkStoreAvailability":false,"intent":false,"inventoryStatus":null,"locationText":"Lake Worth Supercenter","maxOrderQuantity":null,"orderLimit":null,"productLocation":null,"selected":false,"speedDetails":null,"storeName":null,"subscriptionSubmessage":"NONE","type":"PICKUP"},{"__typename":"DeliveryOptionV2","availabilityStatus":"NOT_AVAILABLE","availableQuantity":null,"intent":false,"locationText":"Lake Worth, 33467","maxOrderQuantity":null,"orderLimit":null,"selected":false,"speedDetails":null,"subscriptionSubmessage":"NONE","type":"DELIVERY"}],"sellerId":"E88F7D811B9D40C296D35F8D9AB1C003","shipAsIs":false}