{"isWplusMember":false,"viscosity":null,"showSubscriptionModule":false,"fulfillmentTitle":"title_shipToHome_date_delivery","gender":"Male","petRxEligible":null,"brand":"Disney Pixar","id":"14TRVO9N4WM6","fulfillmentTypeClassification":null,"model":null,"buyBoxSuppression":false,"eventAttributes":{"priceFlip":false,"specialBuy":false},"transactableOfferCount":1,"snapEligible":false,"personalizable":false,"weightIncrement":1,"showAddOnServices":true,"tireSize":null,"experienceType":null,"brandUrl":"/c/brand/disney-pixar","secondaryOfferPrice":{"currentPrice":null},"showFulfillmentLink":false,"wfsEnabled":true,"preOrder":{"isPreOrder":false},"additionalOfferCount":null,"category":{"categoryPathId":"0:5438:7712430:2299833:9207206:9007948:6002189","path":[{"name":"Clothing","url":"/cp/clothing/5438"},{"name":"Kids Clothing","url":"/cp/kids-clothing/7712430"},{"name":"Kids Clothing Character Shop","url":"/cp/kids-clothing-character-shop/2299833"},{"name":"Kids Character Shop","url":"/cp/kids-character-shop/9207206"},{"name":"Boys Character Shop","url":"/cp/boys-character-shop/9007948"},{"name":"Boys Character Clothing","url":"/cp/boys-character-clothing/6002189"}]},"langUrls":null,"type":"Sweatshirts & Hoodies","selectedVariantIds":["actual_color-toystory","clothing_size-6"],"sellerDisplayName":"imagikids","ebooks":null,"maxRewardAmongAllVariants":null,"subscription":{"showSubscriptionModule":false,"subscriptionEligible":false,"subscriptionSubmessage":"NONE","subscriptionTransactable":false},"fulfillmentSummary":[{"calculatedSlaDays":null,"deliveryDate":"2023-12-18T22:59:00.000Z","fulfillment":"DELIVERY","fulfillmentBadge":"2 days","fulfillmentMethods":["UNSCHEDULED"],"isFreeForWPlus":null,"sla":{"measurementValue":4,"unitOfMeasure":"DAY"},"storeId":"0"}],"offerType":"ONLINE_ONLY","returnPolicy":{"freeReturns":true,"holidayReturnEnabled":false,"returnPolicyCondition":null,"returnPolicyText":"Free 90-day returns","returnWindow":{"unitType":"Day","value":90},"returnable":true},"shortDescription":"The toys are back and ready to have another unforgettable laugh-out-loud adventure, so get dressed! Join Sheriff Woody, space ranger Buzz Lightyear, Jessie the cowgirl and company on their latest journey out of the toy box, to infinity and beyond. Your little one will feel like the new Andy or Bonnie in this Disney Pixar Toy Story Hoodie as they dodge The Claw with the green Aliens at Pizza Planet, switch up Mr. and Mrs. Potato Head’s hilarious faces, cross the street under cones with Slinky Dog, play Attack on Zurg with Rex the dinosaur and Hamm the piggy bank, help Bo-Peep return lost toys home, and at the end of it all, ride off into the sunset on the lovable toy horse Bullseye. With your child on their side, these faithful toys from the iconic and groundbreaking Toy Story films will be singing “You’ve Got a Friend in Me” in no time. Your little one will look so adorable and cool in this cute, comfy and stylish long sleeve graphic hooded sweatshirt featuring their favorite animated movies that they’ll always love wearing it.","usItemId":"273542979","offerId":"052F4472F0CD4331B55FA4249B58C6E9","fulfillmentBadge":"2 days","checkAvailabilityGlobalDFS":false,"variantProductIdMap":{"actual_color-toystory-clothing_size-10":"5CS29TYD9PJM","actual_color-toystory-clothing_size-12":"3FUVUK743YLF","actual_color-toystory-clothing_size-2t":"2DI8LSGK0SCV","actual_color-toystory-clothing_size-3t":"2FEQRSLAT99K","actual_color-toystory-clothing_size-4t":"6IRWM7JMV9C7","actual_color-toystory-clothing_size-5t":"3KA9ITEA05W5","actual_color-toystory-clothing_size-6":"14TRVO9N4WM6","actual_color-toystory-clothing_size-7":"2GQRODW7LBIH","actual_color-toystory-clothing_size-8":"5Y0A3OXKDYJM"},"orderMinLimit":1,"discounts":null,"displayOfferLevelImage":null,"sellerAverageRating":4.5493,"preownedCondition":null,"tireSpeedRating":null,"fsaEligibleInd":false,"externalInfo":null,"subscriptionEligible":false,"wfsProviderName":null,"suppressReviews":false,"pickupOption":{"accessTypes":[],"availabilityStatus":null,"slaTier":null,"storeId":null,"storeName":null},"rhPath":"50000:52000:52003:52112:52473","variantCriteria":[{"categoryTypeAllValues":"IMAGE_NONTRANSACTIONAL","id":"actual_color","isFitPredictable":false,"isSizeChartApplicable":false,"name":"Color","type":"SWATCH","variantList":[{"availabilityStatus":"AVAILABLE","id":"actual_color-toystory","images":["B0559BDAC88C47789DFDBF93BF409CCC","42733D81D44B4E94BCB8E2E757E0ED5F","F1D67986ACE048459B676685EC22F227","6C32B2416912494693900CED642BE842","F1773BA416904824A1F038E491BACD2D"],"name":"Toy story","products":["2FEQRSLAT99K","3FUVUK743YLF","14TRVO9N4WM6","6IRWM7JMV9C7","3KA9ITEA05W5","2DI8LSGK0SCV","5CS29TYD9PJM","2GQRODW7LBIH","5Y0A3OXKDYJM"],"selected":true,"swatchImageUrl":"https://i5.walmartimages.com/asr/771656ea-7203-468f-ac19-7769ceb555b0.f84fc10e46961b5fdffd0c4fa183d805.jpeg"}]},{"categoryTypeAllValues":"TEXT_NONTRANSACTIONAL","id":"clothing_size","isFitPredictable":true,"isSizeChartApplicable":true,"name":"Clothing Size","type":"DROPDOWN","variantList":[{"availabilityStatus":"AVAILABLE","id":"clothing_size-2t","images":null,"name":"2T","products":["2DI8LSGK0SCV"],"selected":false,"swatchImageUrl":null},{"availabilityStatus":"AVAILABLE","id":"clothing_size-3t","images":null,"name":"3T","products":["2FEQRSLAT99K"],"selected":false,"swatchImageUrl":null},{"availabilityStatus":"AVAILABLE","id":"clothing_size-4t","images":null,"name":"4T","products":["6IRWM7JMV9C7"],"selected":false,"swatchImageUrl":null},{"availabilityStatus":"AVAILABLE","id":"clothing_size-5t","images":null,"name":"5T","products":["3KA9ITEA05W5"],"selected":false,"swatchImageUrl":null},{"availabilityStatus":"AVAILABLE","id":"clothing_size-6","images":null,"name":"6","products":["14TRVO9N4WM6"],"selected":true,"swatchImageUrl":null},{"availabilityStatus":"AVAILABLE","id":"clothing_size-7","images":null,"name":"7","products":["2GQRODW7LBIH"],"selected":false,"swatchImageUrl":null},{"availabilityStatus":"AVAILABLE","id":"clothing_size-8","images":null,"name":"8","products":["5Y0A3OXKDYJM"],"selected":false,"swatchImageUrl":null},{"availabilityStatus":"AVAILABLE","id":"clothing_size-10","images":null,"name":"10","products":["5CS29TYD9PJM"],"selected":false,"swatchImageUrl":null},{"availabilityStatus":"AVAILABLE","id":"clothing_size-12","images":null,"name":"12","products":["3FUVUK743YLF"],"selected":false,"swatchImageUrl":null}]}],"classType":"VARIANT","annualEvent":false,"itemType":null,"sellerName":"imagikids","priceInfo":{"capType":null,"comparisonPrice":null,"currentPrice":{"bestValue":null,"currencyUnit":"USD","price":21.99,"priceDisplay":"$21.99","priceString":"$21.99","variantPriceString":"$21.99"},"isPriceReduced":false,"listPrice":null,"priceDisplayCodes":{"clearance":null,"eligibleForAssociateDiscount":null,"finalCostByWeight":null,"priceDisplayCondition":null,"reducedPrice":null,"rollback":null,"submapType":null},"priceRange":{"currencyUnit":null,"denominations":null,"maxPrice":null,"minPrice":null,"priceString":null},"priceReducedDisplay":null,"savings":null,"savingsAmount":null,"secondaryOfferBoost":null,"shipPrice":null,"subscriptionPrice":null,"unitPrice":null,"wPlusEarlyAccessPrice":null,"walmartFundedAmount":null,"wasPrice":null},"productTypeId":"897","vision":{"ageGroup":"Child","visionCenterApproved":false},"motorOilType":null,"location":{"addressId":null,"city":"Endicott","intent":"SHIPPING","mpPickupLocation":null,"pickupLocation":{"accessPointId":null,"accessType":null,"storeId":"1835"},"postalCode":"13760","stateOrProvinceCode":"NY","storeIds":["1835"]},"earlyAccessEvent":false,"addOnServices":null,"availabilityInNearbyStore":null,"sellerReviewCount":1571,"aaiaBrandId":null,"primaryUsItemId":"273542979","classId":"46","manufacturerProductId":"B9H8729T4","showBuyWithWplus":false,"hasCarePlans":false,"isEarlyAccessItem":false,"ozarkAttributes":{"exactAddress":false,"shippingPromise":"NATIONAL_CARRIER"},"fulfillmentLabel":[{"addressEligibility":true,"checkStoreAvailability":null,"fulfillmentMethod":"SHIPPING","fulfillmentText":"arrives by Mon, Dec 18","fulfillmentType":"FC","locationText":"Endicott, 13760","message":"Shipping, arrives by Mon, Dec 18 to Endicott, 13760","postalCode":"13760","shippingText":"Shipping","wPlusFulfillmentText":null}],"sellerType":"EXTERNAL","zeekitData":null,"variantsMap":{"14TRVO9N4WM6":{"availabilityStatus":"IN_STOCK","buyBoxSuppression":false,"discountPriceString":"","fulfillmentBadge":"2 days","id":"14TRVO9N4WM6","imageInfo":{"allImages":[{"id":"B0559BDAC88C47789DFDBF93BF409CCC","url":"https://i5.walmartimages.com/seo/Disney-Pixar-Toy-Story-Buzz-Lightyear-Woody-Little-Boys-Fleece-Half-Zip-Hoodie-6_e5701094-ad35-4592-883d-118d4ffb9b41.a9a443b55a0692b8d2ce6812c09e6c8d.jpeg","zoomable":true},{"id":"42733D81D44B4E94BCB8E2E757E0ED5F","url":"https://i5.walmartimages.com/asr/bf60e556-8715-4413-ae88-e340d3b7e7a4.cf807f5ccc9fbd0cadb66afe5b6819a0.jpeg","zoomable":true},{"id":"F1D67986ACE048459B676685EC22F227","url":"https://i5.walmartimages.com/asr/2bfc7cd5-12f0-41ea-9482-99d7e602f3c2.5f5ee95d81a23444611c8769760f4f39.jpeg","zoomable":true},{"id":"6C32B2416912494693900CED642BE842","url":"https://i5.walmartimages.com/asr/ffe4fc91-f7dd-458a-9e4d-b0b02247a76b.1b141aa07a650fa021f01dc42b918cdc.jpeg","zoomable":true},{"id":"F1773BA416904824A1F038E491BACD2D","url":"https://i5.walmartimages.com/asr/35a31488-0c3d-4a18-a407-a4414d09ab36.178381e360d4bb71d380c1d967251428.jpeg","zoomable":true}],"thumbnailUrl":"https://i5.walmartimages.com/seo/Disney-Pixar-Toy-Story-Buzz-Lightyear-Woody-Little-Boys-Fleece-Half-Zip-Hoodie-6_e5701094-ad35-4592-883d-118d4ffb9b41.a9a443b55a0692b8d2ce6812c09e6c8d.jpeg"},"priceInfo":{"capType":null,"comparisonPrice":null,"currentPrice":{"bestValue":null,"currencyUnit":"USD","price":21.99,"priceDisplay":"$21.99","priceString":"$21.99","variantPriceString":"$21.99"},"isPriceReduced":false,"listPrice":null,"priceDisplayCodes":{"clearance":null,"eligibleForAssociateDiscount":null,"finalCostByWeight":null,"priceDisplayCondition":null,"reducedPrice":null,"rollback":null,"submapType":null},"priceRange":{"currencyUnit":null,"denominations":null,"maxPrice":null,"minPrice":null,"priceString":null},"priceReducedDisplay":null,"savings":null,"savingsAmount":null,"secondaryOfferBoost":null,"shipPrice":null,"subscriptionPrice":null,"unitPrice":null,"wPlusEarlyAccessPrice":null,"walmartFundedAmount":null,"wasPrice":null},"productUrl":"/ip/Disney-Pixar-Toy-Story-Buzz-Lightyear-Woody-Little-Boys-Fleece-Half-Zip-Hoodie-6/273542979","subscriptionEligible":false,"usItemId":"273542979","variants":["actual_color-toystory","clothing_size-6"]},"2DI8LSGK0SCV":{"availabilityStatus":"IN_STOCK","buyBoxSuppression":false,"discountPriceString":"","fulfillmentBadge":"2 days","id":"2DI8LSGK0SCV","imageInfo":{"allImages":[],"thumbnailUrl":null},"priceInfo":{"currentPrice":{"bestValue":null,"currencyUnit":"USD","price":21.99,"priceString":"$21.99","variantPriceString":"$21.99"},"isPriceReduced":false,"listPrice":null,"priceDisplayCodes":{"clearance":null,"eligibleForAssociateDiscount":null,"finalCostByWeight":null,"priceDisplayCondition":null,"reducedPrice":null,"rollback":null,"submapType":null},"priceReducedDisplay":null,"savingsAmount":null,"secondaryOfferBoost":null,"unitPrice":null,"wasPrice":null},"productUrl":"/ip/Disney-Pixar-Toy-Story-Buzz-Lightyear-Woody-Toddler-Boys-Fleece-Half-Zip-Hoodie-2T/19477515","subscriptionEligible":false,"usItemId":"19477515","variants":["actual_color-toystory","clothing_size-2t"]},"2FEQRSLAT99K":{"availabilityStatus":"IN_STOCK","buyBoxSuppression":false,"discountPriceString":"","fulfillmentBadge":"2 days","id":"2FEQRSLAT99K","imageInfo":{"allImages":[],"thumbnailUrl":null},"priceInfo":{"currentPrice":{"bestValue":null,"currencyUnit":"USD","price":21.99,"priceString":"$21.99","variantPriceString":"$21.99"},"isPriceReduced":false,"listPrice":null,"priceDisplayCodes":{"clearance":null,"eligibleForAssociateDiscount":null,"finalCostByWeight":null,"priceDisplayCondition":null,"reducedPrice":null,"rollback":null,"submapType":null},"priceReducedDisplay":null,"savingsAmount":null,"secondaryOfferBoost":null,"unitPrice":null,"wasPrice":null},"productUrl":"/ip/Disney-Pixar-Toy-Story-Buzz-Lightyear-Woody-Toddler-Boys-Fleece-Half-Zip-Hoodie-3T/19477514","subscriptionEligible":false,"usItemId":"19477514","variants":["actual_color-toystory","clothing_size-3t"]},"2GQRODW7LBIH":{"availabilityStatus":"IN_STOCK","buyBoxSuppression":false,"discountPriceString":"","fulfillmentBadge":"2 days","id":"2GQRODW7LBIH","imageInfo":{"allImages":[],"thumbnailUrl":null},"priceInfo":{"currentPrice":{"bestValue":null,"currencyUnit":"USD","price":21.99,"priceString":"$21.99","variantPriceString":"$21.99"},"isPriceReduced":false,"listPrice":null,"priceDisplayCodes":{"clearance":null,"eligibleForAssociateDiscount":null,"finalCostByWeight":null,"priceDisplayCondition":null,"reducedPrice":null,"rollback":null,"submapType":null},"priceReducedDisplay":null,"savingsAmount":null,"secondaryOfferBoost":null,"unitPrice":null,"wasPrice":null},"productUrl":"/ip/Disney-Pixar-Toy-Story-Buzz-Lightyear-Woody-Little-Boys-Fleece-Half-Zip-Hoodie-7/741922008","subscriptionEligible":false,"usItemId":"741922008","variants":["actual_color-toystory","clothing_size-7"]},"3FUVUK743YLF":{"availabilityStatus":"IN_STOCK","buyBoxSuppression":false,"discountPriceString":"","fulfillmentBadge":"2 days","id":"3FUVUK743YLF","imageInfo":{"allImages":[],"thumbnailUrl":null},"priceInfo":{"currentPrice":{"bestValue":null,"currencyUnit":"USD","price":21.99,"priceString":"$21.99","variantPriceString":"$21.99"},"isPriceReduced":false,"listPrice":null,"priceDisplayCodes":{"clearance":null,"eligibleForAssociateDiscount":null,"finalCostByWeight":null,"priceDisplayCondition":null,"reducedPrice":null,"rollback":null,"submapType":null},"priceReducedDisplay":null,"savingsAmount":null,"secondaryOfferBoost":null,"unitPrice":null,"wasPrice":null},"productUrl":"/ip/Disney-Pixar-Toy-Story-Buzz-Lightyear-Woody-Big-Boys-Fleece-Half-Zip-Hoodie-12/844586565","subscriptionEligible":false,"usItemId":"844586565","variants":["actual_color-toystory","clothing_size-12"]},"3KA9ITEA05W5":{"availabilityStatus":"IN_STOCK","buyBoxSuppression":false,"discountPriceString":"","fulfillmentBadge":"2 days","id":"3KA9ITEA05W5","imageInfo":{"allImages":[],"thumbnailUrl":null},"priceInfo":{"currentPrice":{"bestValue":null,"currencyUnit":"USD","price":21.99,"priceString":"$21.99","variantPriceString":"$21.99"},"isPriceReduced":false,"listPrice":null,"priceDisplayCodes":{"clearance":null,"eligibleForAssociateDiscount":null,"finalCostByWeight":null,"priceDisplayCondition":null,"reducedPrice":null,"rollback":null,"submapType":null},"priceReducedDisplay":null,"savingsAmount":null,"secondaryOfferBoost":null,"unitPrice":null,"wasPrice":null},"productUrl":"/ip/Disney-Pixar-Toy-Story-Buzz-Lightyear-Woody-Toddler-Boys-Fleece-Half-Zip-Hoodie-5T/349266385","subscriptionEligible":false,"usItemId":"349266385","variants":["actual_color-toystory","clothing_size-5t"]},"5CS29TYD9PJM":{"availabilityStatus":"IN_STOCK","buyBoxSuppression":false,"discountPriceString":"","fulfillmentBadge":"2 days","id":"5CS29TYD9PJM","imageInfo":{"allImages":[],"thumbnailUrl":null},"priceInfo":{"currentPrice":{"bestValue":null,"currencyUnit":"USD","price":21.99,"priceString":"$21.99","variantPriceString":"$21.99"},"isPriceReduced":false,"listPrice":null,"priceDisplayCodes":{"clearance":null,"eligibleForAssociateDiscount":null,"finalCostByWeight":null,"priceDisplayCondition":null,"reducedPrice":null,"rollback":null,"submapType":null},"priceReducedDisplay":null,"savingsAmount":null,"secondaryOfferBoost":null,"unitPrice":null,"wasPrice":null},"productUrl":"/ip/Disney-Pixar-Toy-Story-Buzz-Lightyear-Woody-Big-Boys-Fleece-Half-Zip-Hoodie-10/199451443","subscriptionEligible":false,"usItemId":"199451443","variants":["actual_color-toystory","clothing_size-10"]},"5Y0A3OXKDYJM":{"availabilityStatus":"IN_STOCK","buyBoxSuppression":false,"discountPriceString":"","fulfillmentBadge":"2 days","id":"5Y0A3OXKDYJM","imageInfo":{"allImages":[],"thumbnailUrl":null},"priceInfo":{"currentPrice":{"bestValue":null,"currencyUnit":"USD","price":21.99,"priceString":"$21.99","variantPriceString":"$21.99"},"isPriceReduced":false,"listPrice":null,"priceDisplayCodes":{"clearance":null,"eligibleForAssociateDiscount":null,"finalCostByWeight":null,"priceDisplayCondition":null,"reducedPrice":null,"rollback":null,"submapType":null},"priceReducedDisplay":null,"savingsAmount":null,"secondaryOfferBoost":null,"unitPrice":null,"wasPrice":null},"productUrl":"/ip/Disney-Pixar-Toy-Story-Buzz-Lightyear-Woody-Big-Boys-Fleece-Half-Zip-Hoodie-8/686452231","subscriptionEligible":false,"usItemId":"686452231","variants":["actual_color-toystory","clothing_size-8"]},"6IRWM7JMV9C7":{"availabilityStatus":"IN_STOCK","buyBoxSuppression":false,"discountPriceString":"","fulfillmentBadge":"2 days","id":"6IRWM7JMV9C7","imageInfo":{"allImages":[],"thumbnailUrl":null},"priceInfo":{"currentPrice":{"bestValue":null,"currencyUnit":"USD","price":21.99,"priceString":"$21.99","variantPriceString":"$21.99"},"isPriceReduced":false,"listPrice":null,"priceDisplayCodes":{"clearance":null,"eligibleForAssociateDiscount":null,"finalCostByWeight":null,"priceDisplayCondition":null,"reducedPrice":null,"rollback":null,"submapType":null},"priceReducedDisplay":null,"savingsAmount":null,"secondaryOfferBoost":null,"unitPrice":null,"wasPrice":null},"productUrl":"/ip/Disney-Pixar-Toy-Story-Buzz-Lightyear-Woody-Toddler-Boys-Fleece-Half-Zip-Hoodie-4T/437834779","subscriptionEligible":false,"usItemId":"437834779","variants":["actual_color-toystory","clothing_size-4t"]}},"giftingEligibility":false,"shippingOption":{"availabilityStatus":"AVAILABLE","deliveryDate":"2023-12-18T22:59:00.000Z","internationalShipping":null,"maxDeliveryDate":null,"shipMethod":null,"shipPrice":null,"slaTier":"TWO_DAY"},"legalRestriction":false,"ironbankCategory":"Clothing","catalogSellerId":8617,"salesUnit":"EACH","fulfillmentType":"FC","petRx":{"eligible":false,"singleDispense":null},"averageRating":4.3,"pac":null,"badges":{"flags":null,"groups":[],"labels":null,"tags":[]},"showExploreOtherConditionsCTA":false,"variants":[],"hasHomeServices":null,"promoData":[],"conditionType":null,"imageInfo":{"allImages":[{"id":"B0559BDAC88C47789DFDBF93BF409CCC","url":"https://i5.walmartimages.com/seo/Disney-Pixar-Toy-Story-Buzz-Lightyear-Woody-Little-Boys-Fleece-Half-Zip-Hoodie-6_e5701094-ad35-4592-883d-118d4ffb9b41.a9a443b55a0692b8d2ce6812c09e6c8d.jpeg","zoomable":true},{"id":"42733D81D44B4E94BCB8E2E757E0ED5F","url":"https://i5.walmartimages.com/asr/bf60e556-8715-4413-ae88-e340d3b7e7a4.cf807f5ccc9fbd0cadb66afe5b6819a0.jpeg","zoomable":true},{"id":"F1D67986ACE048459B676685EC22F227","url":"https://i5.walmartimages.com/asr/2bfc7cd5-12f0-41ea-9482-99d7e602f3c2.5f5ee95d81a23444611c8769760f4f39.jpeg","zoomable":true},{"id":"6C32B2416912494693900CED642BE842","url":"https://i5.walmartimages.com/asr/ffe4fc91-f7dd-458a-9e4d-b0b02247a76b.1b141aa07a650fa021f01dc42b918cdc.jpeg","zoomable":true},{"id":"F1773BA416904824A1F038E491BACD2D","url":"https://i5.walmartimages.com/asr/35a31488-0c3d-4a18-a407-a4414d09ab36.178381e360d4bb71d380c1d967251428.jpeg","zoomable":true}],"thumbnailUrl":"https://i5.walmartimages.com/seo/Disney-Pixar-Toy-Story-Buzz-Lightyear-Woody-Little-Boys-Fleece-Half-Zip-Hoodie-6_e5701094-ad35-4592-883d-118d4ffb9b41.a9a443b55a0692b8d2ce6812c09e6c8d.jpeg"},"tireLoadIndex":null,"productLocation":null,"checkStoreAvailabilityATC":false,"hasSellerBadge":true,"imageMap":{"42733D81D44B4E94BCB8E2E757E0ED5F":{"id":"42733D81D44B4E94BCB8E2E757E0ED5F","url":"https://i5.walmartimages.com/asr/bf60e556-8715-4413-ae88-e340d3b7e7a4.cf807f5ccc9fbd0cadb66afe5b6819a0.jpeg","zoomable":true},"6C32B2416912494693900CED642BE842":{"id":"6C32B2416912494693900CED642BE842","url":"https://i5.walmartimages.com/asr/ffe4fc91-f7dd-458a-9e4d-b0b02247a76b.1b141aa07a650fa021f01dc42b918cdc.jpeg","zoomable":true},"B0559BDAC88C47789DFDBF93BF409CCC":{"id":"B0559BDAC88C47789DFDBF93BF409CCC","url":"https://i5.walmartimages.com/seo/Disney-Pixar-Toy-Story-Buzz-Lightyear-Woody-Little-Boys-Fleece-Half-Zip-Hoodie-6_e5701094-ad35-4592-883d-118d4ffb9b41.a9a443b55a0692b8d2ce6812c09e6c8d.jpeg","zoomable":true},"F1773BA416904824A1F038E491BACD2D":{"id":"F1773BA416904824A1F038E491BACD2D","url":"https://i5.walmartimages.com/asr/35a31488-0c3d-4a18-a407-a4414d09ab36.178381e360d4bb71d380c1d967251428.jpeg","zoomable":true},"F1D67986ACE048459B676685EC22F227":{"id":"F1D67986ACE048459B676685EC22F227","url":"https://i5.walmartimages.com/asr/2bfc7cd5-12f0-41ea-9482-99d7e602f3c2.5f5ee95d81a23444611c8769760f4f39.jpeg","zoomable":true}},"newConditionProductId":null,"upc":"024054091739","redirect":{"replacedByItemId":"","replacedByProductId":"","replacedByProductUrlText":""},"shippingRestriction":false,"availabilityStatus":"IN_STOCK","blitzItem":null,"promoDiscount":null,"rewards":null,"associatedBundleId":null,"orderLimit":12,"numberOfReviews":23,"isPreowned":false,"buyNowEligible":true,"semStoreData":null,"canonicalUrl":"/ip/Disney-Pixar-Toy-Story-Buzz-Lightyear-Woody-Little-Boys-Fleece-Half-Zip-Hoodie-6/273542979","groupMetaData":null,"name":"Disney Pixar Toy Story Buzz Lightyear Woody Little Boys Fleece Half Zip Hoodie 6","fulfillmentOptions":[{"__typename":"ShippingOptionV2","availabilityStatus":"IN_STOCK","availableQuantity":114,"intent":true,"inventoryStatus":null,"locationText":"Endicott, 13760","maxOrderQuantity":12,"orderLimit":12,"restricted":false,"selected":false,"speedDetails":{"deliveryDate":"2023-12-18T22:59:00.000Z","freeFulfillment":false,"fulfillmentBadge":null,"fulfillmentPrice":null,"wPlusEligible":false},"subscriptionSubmessage":"NONE","type":"SHIPPING"},{"__typename":"PickupOptionV2","availabilityStatus":"NOT_AVAILABLE","availableQuantity":null,"checkStoreAvailability":false,"intent":false,"inventoryStatus":null,"locationText":"Vestal Supercenter","maxOrderQuantity":null,"orderLimit":null,"productLocation":null,"selected":false,"speedDetails":null,"storeName":null,"subscriptionSubmessage":"NONE","type":"PICKUP"},{"__typename":"DeliveryOptionV2","availabilityStatus":"NOT_AVAILABLE","availableQuantity":null,"intent":false,"locationText":"Endicott, 13760","maxOrderQuantity":null,"orderLimit":null,"selected":false,"speedDetails":null,"subscriptionSubmessage":"NONE","type":"DELIVERY"}],"sellerId":"0EE4DF6A2B5C40D7A9DD1FE44D472685","shipAsIs":false}