{"isWplusMember":false,"viscosity":null,"showSubscriptionModule":false,"fulfillmentTitle":"title_shipToHome_date_delivery","gender":null,"petRxEligible":null,"brand":"Rust-Oleum","id":"2WOXM1J0NL7M","fulfillmentTypeClassification":null,"model":"372010","buyBoxSuppression":false,"eventAttributes":{"priceFlip":false,"specialBuy":false},"transactableOfferCount":2,"snapEligible":false,"personalizable":false,"weightIncrement":1,"showAddOnServices":true,"tireSize":null,"experienceType":null,"brandUrl":"/c/brand/rust-oleum","secondaryOfferPrice":{"currentPrice":{"price":29.06,"priceString":"$29.06","priceType":null}},"showFulfillmentLink":false,"wfsEnabled":false,"preOrder":{"isPreOrder":false},"additionalOfferCount":1,"category":{"categoryPathId":"0:1072864:1067617:1067620:9317037","path":[{"name":"Home Improvement","url":"/cp/home-improvement/1072864"},{"name":"Paint","url":"/cp/paint/1067617"},{"name":"Interior Paint","url":"/cp/interior-paint/1067620"},{"name":"Trim Paint","url":"/cp/trim-paint/9317037"}]},"langUrls":null,"type":"Household Paints & Stains","selectedVariantIds":["actual_color-darkgray","count_per_pack-1","paint_finish-semi-gloss"],"sellerDisplayName":"Walmart.com","ebooks":null,"maxRewardAmongAllVariants":null,"subscription":{"showSubscriptionModule":false,"subscriptionEligible":false,"subscriptionSubmessage":"NONE","subscriptionTransactable":false},"fulfillmentSummary":[{"calculatedSlaDays":null,"deliveryDate":"2023-12-17T22:59:00.000Z","fulfillment":"DELIVERY","fulfillmentBadge":null,"fulfillmentMethods":["UNSCHEDULED"],"isFreeForWPlus":null,"sla":{"measurementValue":3,"unitOfMeasure":"DAY"},"storeId":"0"}],"offerType":"ONLINE_AND_STORE","returnPolicy":{"freeReturns":true,"holidayReturnEnabled":false,"returnPolicyCondition":null,"returnPolicyText":"Free 90-day returns","returnWindow":{"unitType":"Day","value":90},"returnable":true},"shortDescription":"Dark Gray, Rust-Oleum Transformations  Semi-Gloss Cabinet & Trim Paint-372010, Quart: Provides simple, beautiful results for do-it-yourself kitchen and bathroom remodel projects. Easy to use, 1-step cabinet paint offers an affordable alternative to cabinet replacement with a durable, semi-gloss finish. Update interior cabinets, vanities and more for a quick home makeover. Use with Zinsser bulls eye 1-2-3 primer or B-I-N primer-sealer for superior adhesion and hiding over bare wood or dark colors. Dries to the touch in 30-minutes, recoat after 2-hours.","usItemId":"685411720","offerId":"FA79B03D231641A48939771FFEE506CC","fulfillmentBadge":null,"checkAvailabilityGlobalDFS":false,"variantProductIdMap":{"actual_color-black-count_per_pack-1-paint_finish-semi-gloss":"2FX9FY49RJXQ","actual_color-black-count_per_pack-4-paint_finish-semi-gloss":"64LF3R8QOAKK","actual_color-cadetgray-count_per_pack-1-paint_finish-semi-gloss":"556ZYK1IYWMH","actual_color-cadetgray-count_per_pack-4-paint_finish-semi-gloss":"14EWKGDI2R0W","actual_color-darkgray-count_per_pack-1-paint_finish-semi-gloss":"2WOXM1J0NL7M","actual_color-darkgray-count_per_pack-4-paint_finish-semi-gloss":"36A7S10D0KPJ","actual_color-espresso-count_per_pack-1-paint_finish-semi-gloss":"4EYNLLUXH0LF","actual_color-linen-count_per_pack-1-paint_finish-semi-gloss":"23L0BGGMANS8","actual_color-linen-count_per_pack-4-paint_finish-semi-gloss":"6Y420GWQDK12","actual_color-purewhite-count_per_pack-1-paint_finish-semi-gloss":"652S3L4JL02R","actual_color-purewhite-count_per_pack-4-paint_finish-semi-gloss":"5R4S9HG6FKUD"},"orderMinLimit":1,"discounts":null,"displayOfferLevelImage":null,"sellerAverageRating":null,"preownedCondition":null,"tireSpeedRating":null,"fsaEligibleInd":false,"externalInfo":null,"subscriptionEligible":false,"wfsProviderName":null,"suppressReviews":false,"pickupOption":{"accessTypes":[],"availabilityStatus":null,"slaTier":null,"storeId":null,"storeName":null},"rhPath":"30000:32000:32004:32113:32508","variantCriteria":[{"categoryTypeAllValues":"IMAGE_NONTRANSACTIONAL","id":"actual_color","isFitPredictable":false,"isSizeChartApplicable":false,"name":"Actual Color","type":"SWATCH","variantList":[{"availabilityStatus":"AVAILABLE","id":"actual_color-black","images":["CB46DABCEA454E7E9167AFE1A69AA339","3036D0E9F1D748A8B1F3B29A583D048B","20BB2374AFD846EEB7DD033869E67B8C","C4FCBE7BF3E449D4AC90158024B54944","43120921985D4512806DE4AAB78926A0"],"name":"Black","products":["2FX9FY49RJXQ","64LF3R8QOAKK"],"selected":false,"swatchImageUrl":"https://i5.walmartimages.com/asr/3f8acfe5-8434-47fe-ad1c-82ffcf2a60d7.a552594bb9713bbdc14909e091f5e97c.jpeg"},{"availabilityStatus":"AVAILABLE","id":"actual_color-cadetgray","images":["FAA8B894575B4F9E867328A44F913132","50821655A79A4A6C97AEB061DAAF63A2","8CFC02A63FA24057BF047D6CF5E12414","F84B0D60B35F429FA6AC227CB73B18A3","43120921985D4512806DE4AAB78926A0"],"name":"Cadet Gray","products":["556ZYK1IYWMH","14EWKGDI2R0W"],"selected":false,"swatchImageUrl":"https://i5.walmartimages.com/asr/d381bbd3-bd63-4410-8c32-e28eab346d2b.4871682e628f2011c6d3cadd215a124b.jpeg"},{"availabilityStatus":"AVAILABLE","id":"actual_color-darkgray","images":["92B05E2E300A468BB6AE85441BB53027","221C7A4511DA468C8E4AEF4D82108AC2","3C06D947C9064CADBFB7526038A0096A","E9CCEF59621B4A4E8BDBCE24B3CBD313","43120921985D4512806DE4AAB78926A0"],"name":"Dark Gray","products":["2WOXM1J0NL7M","36A7S10D0KPJ"],"selected":true,"swatchImageUrl":"https://i5.walmartimages.com/asr/5f21c46d-4faf-4380-bfe4-f67f818da3cd.dbb654a0e883a43033da3585327500d1.jpeg"},{"availabilityStatus":"AVAILABLE","id":"actual_color-espresso","images":["832397CBF9D046BC9B40056CA7794C20","63D2CC019CC44C13AAA113240385E56B","70DD250CE9324DDDB8A2C068E021AA02","43120921985D4512806DE4AAB78926A0"],"name":"Espresso","products":["4EYNLLUXH0LF"],"selected":false,"swatchImageUrl":"https://i5.walmartimages.com/asr/996334d6-1b04-4dbc-b291-cdc2a94980b2.2cec7644cf0b2c6fbbe70b1283d28fb7.jpeg"},{"availabilityStatus":"AVAILABLE","id":"actual_color-linen","images":["39164D985D344EE5957623205B2FE23F","84D18F41D73E4E329EA841A4FE986F35","3486004DAD284DE885965DC838FC8A84","15B26A6DBB504F85B799B4BE1E25934C","43120921985D4512806DE4AAB78926A0"],"name":"Linen","products":["23L0BGGMANS8","6Y420GWQDK12"],"selected":false,"swatchImageUrl":"https://i5.walmartimages.com/asr/86fd1340-761d-459a-8a5a-8b9c3b0dd72d.6a854095a371d4a7767783a90c2378b4.jpeg"},{"availabilityStatus":"AVAILABLE","id":"actual_color-purewhite","images":["143ADFDD2E7B46428C9F41F7BF304AD7","D2EDBD9C09A2488EBA774865E75DA6D7","0DB1168DDB17440DAEED26D5DF980850","6DF9666233664C38B954FACDCF90B2D8","43120921985D4512806DE4AAB78926A0"],"name":"Pure White","products":["652S3L4JL02R","5R4S9HG6FKUD"],"selected":false,"swatchImageUrl":"https://i5.walmartimages.com/asr/3c7ad0d1-41c8-4510-89c3-5750ba6a2f33.860cb2167ee9c5e46cb64ed33e8741fd.jpeg"}]},{"categoryTypeAllValues":null,"id":"count_per_pack","isFitPredictable":false,"isSizeChartApplicable":false,"name":"Count Per Pack","type":"DROPDOWN","variantList":[{"availabilityStatus":"AVAILABLE","id":"count_per_pack-1","images":null,"name":"1","products":["23L0BGGMANS8","556ZYK1IYWMH","652S3L4JL02R","2FX9FY49RJXQ","2WOXM1J0NL7M","4EYNLLUXH0LF"],"selected":true,"swatchImageUrl":null},{"availabilityStatus":"AVAILABLE","id":"count_per_pack-4","images":null,"name":"4","products":["14EWKGDI2R0W","5R4S9HG6FKUD","64LF3R8QOAKK","36A7S10D0KPJ","6Y420GWQDK12"],"selected":false,"swatchImageUrl":null}]},{"categoryTypeAllValues":null,"id":"paint_finish","isFitPredictable":false,"isSizeChartApplicable":false,"name":"Paint Finish","type":"DROPDOWN","variantList":[{"availabilityStatus":"AVAILABLE","id":"paint_finish-semi-gloss","images":null,"name":"Semi-Gloss","products":["23L0BGGMANS8","556ZYK1IYWMH","652S3L4JL02R","14EWKGDI2R0W","2FX9FY49RJXQ","5R4S9HG6FKUD","64LF3R8QOAKK","2WOXM1J0NL7M","36A7S10D0KPJ","6Y420GWQDK12","4EYNLLUXH0LF"],"selected":true,"swatchImageUrl":null}]}],"classType":"VARIANT","annualEvent":false,"itemType":null,"sellerName":"Walmart.com","priceInfo":{"capType":null,"comparisonPrice":null,"currentPrice":{"bestValue":null,"currencyUnit":"USD","price":19.97,"priceDisplay":"$19.97","priceString":"$19.97","variantPriceString":"$19.97"},"isPriceReduced":false,"listPrice":null,"priceDisplayCodes":{"clearance":null,"eligibleForAssociateDiscount":true,"finalCostByWeight":null,"priceDisplayCondition":null,"reducedPrice":null,"rollback":null,"submapType":null},"priceRange":{"currencyUnit":null,"denominations":null,"maxPrice":null,"minPrice":null,"priceString":null},"priceReducedDisplay":null,"savings":null,"savingsAmount":null,"secondaryOfferBoost":null,"shipPrice":null,"subscriptionPrice":null,"unitPrice":null,"wPlusEarlyAccessPrice":null,"walmartFundedAmount":null,"wasPrice":null},"productTypeId":"2384","vision":{"ageGroup":null,"visionCenterApproved":false},"motorOilType":null,"location":{"addressId":null,"city":"Laurel","intent":"SHIPPING","mpPickupLocation":null,"pickupLocation":{"accessPointId":null,"accessType":null,"storeId":"1985"},"postalCode":"20723","stateOrProvinceCode":"MD","storeIds":["1985"]},"earlyAccessEvent":false,"addOnServices":null,"availabilityInNearbyStore":null,"sellerReviewCount":null,"aaiaBrandId":null,"primaryUsItemId":"685411720","classId":"1","manufacturerProductId":"372010","showBuyWithWplus":false,"hasCarePlans":false,"isEarlyAccessItem":false,"ozarkAttributes":{"exactAddress":false,"shippingPromise":"NATIONAL_CARRIER"},"fulfillmentLabel":[{"addressEligibility":true,"checkStoreAvailability":null,"fulfillmentMethod":"SHIPPING","fulfillmentText":"arrives by Sun, Dec 17","fulfillmentType":"FC","locationText":"Laurel, 20723","message":"Shipping, arrives by Sun, Dec 17 to Laurel, 20723","postalCode":"20723","shippingText":"Shipping","wPlusFulfillmentText":null},{"addressEligibility":null,"checkStoreAvailability":"Check availability nearby","fulfillmentMethod":"PICKUP","fulfillmentText":"not available","fulfillmentType":null,"locationText":null,"message":"Pickup not available at Laurel Supercenter","postalCode":null,"shippingText":"Pickup","wPlusFulfillmentText":null}],"sellerType":"INTERNAL","zeekitData":null,"variantsMap":{"14EWKGDI2R0W":{"availabilityStatus":"IN_STOCK","buyBoxSuppression":false,"discountPriceString":"","fulfillmentBadge":null,"id":"14EWKGDI2R0W","imageInfo":{"allImages":[],"thumbnailUrl":null},"priceInfo":{"currentPrice":{"bestValue":null,"currencyUnit":"USD","price":60.14,"priceString":"$60.14","variantPriceString":"$60.14"},"isPriceReduced":true,"listPrice":null,"priceDisplayCodes":{"clearance":null,"eligibleForAssociateDiscount":true,"finalCostByWeight":null,"priceDisplayCondition":null,"reducedPrice":null,"rollback":null,"submapType":null},"priceReducedDisplay":"Now $60.14","savingsAmount":null,"secondaryOfferBoost":null,"unitPrice":{"bestValue":false,"currencyUnit":"USD","price":1.88,"priceString":"$1.88/fl oz","variantPriceString":null},"wasPrice":null},"productUrl":"/ip/Cadet-Gray-Rust-Oleum-Transformations-Semi-Gloss-Cabinet-Trim-Paint-Quart/702673885","subscriptionEligible":false,"usItemId":"702673885","variants":["actual_color-cadetgray","count_per_pack-4","paint_finish-semi-gloss"]},"23L0BGGMANS8":{"availabilityStatus":"IN_STOCK","buyBoxSuppression":false,"discountPriceString":"","fulfillmentBadge":"Tomorrow","id":"23L0BGGMANS8","imageInfo":{"allImages":[{"id":"39164D985D344EE5957623205B2FE23F","url":"https://i5.walmartimages.com/seo/Linen-Rust-Oleum-Transformations-Semi-Gloss-Cabinet-Trim-Paint-372008-Quart_58440b3c-0d5c-494a-ba83-164adad184e4.fa3204c110f4dc28144e04d4830a106e.jpeg","zoomable":true},{"id":"84D18F41D73E4E329EA841A4FE986F35","url":"https://i5.walmartimages.com/asr/8cce319f-70d9-41e5-91e3-76a77d1bc400.5229dce8223a6cd56bd87a10ff1dd8d0.jpeg","zoomable":true},{"id":"3486004DAD284DE885965DC838FC8A84","url":"https://i5.walmartimages.com/asr/86fd1340-761d-459a-8a5a-8b9c3b0dd72d.6a854095a371d4a7767783a90c2378b4.jpeg","zoomable":false},{"id":"15B26A6DBB504F85B799B4BE1E25934C","url":"https://i5.walmartimages.com/asr/6191c2f3-7a81-4bf8-ae55-0d38486e0b96.feee5e2aef60f98df4049e83ec672abc.jpeg","zoomable":true},{"id":"43120921985D4512806DE4AAB78926A0","url":"https://i5.walmartimages.com/asr/c99e86df-2749-4d7c-8b9c-4bafa346e28c.84f5299fee35f6a450bf881773cc8f02.jpeg","zoomable":true}],"thumbnailUrl":"https://i5.walmartimages.com/seo/Linen-Rust-Oleum-Transformations-Semi-Gloss-Cabinet-Trim-Paint-372008-Quart_58440b3c-0d5c-494a-ba83-164adad184e4.fa3204c110f4dc28144e04d4830a106e.jpeg"},"priceInfo":{"currentPrice":{"bestValue":null,"currencyUnit":"USD","price":19.97,"priceString":"$19.97","variantPriceString":"$19.97"},"isPriceReduced":true,"listPrice":null,"priceDisplayCodes":{"clearance":null,"eligibleForAssociateDiscount":true,"finalCostByWeight":null,"priceDisplayCondition":null,"reducedPrice":null,"rollback":null,"submapType":null},"priceReducedDisplay":"Now $19.97","savingsAmount":null,"secondaryOfferBoost":null,"unitPrice":null,"wasPrice":null},"productUrl":"/ip/Linen-Rust-Oleum-Transformations-Semi-Gloss-Cabinet-Trim-Paint-372008-Quart/726402461","subscriptionEligible":false,"usItemId":"726402461","variants":["actual_color-linen","count_per_pack-1","paint_finish-semi-gloss"]},"2FX9FY49RJXQ":{"availabilityStatus":"IN_STOCK","buyBoxSuppression":false,"discountPriceString":"","fulfillmentBadge":null,"id":"2FX9FY49RJXQ","imageInfo":{"allImages":[{"id":"CB46DABCEA454E7E9167AFE1A69AA339","url":"https://i5.walmartimages.com/seo/Black-Rust-Oleum-Transformations-Semi-Gloss-Cabinet-Trim-Paint-372012-Quart_57833487-e596-49cb-99ac-4ef470723517.97b18685b4bc113446863a42ae96f8eb.jpeg","zoomable":true},{"id":"3036D0E9F1D748A8B1F3B29A583D048B","url":"https://i5.walmartimages.com/asr/ceabb1f2-592a-41f1-9fdd-c86a83367d84.1bcf5d4317edb6674466722aad5b373d.jpeg","zoomable":true},{"id":"20BB2374AFD846EEB7DD033869E67B8C","url":"https://i5.walmartimages.com/asr/3f8acfe5-8434-47fe-ad1c-82ffcf2a60d7.a552594bb9713bbdc14909e091f5e97c.jpeg","zoomable":false},{"id":"C4FCBE7BF3E449D4AC90158024B54944","url":"https://i5.walmartimages.com/asr/fec90e3c-59e0-4742-8ce0-9e8389768886.1c99b920e4868c39531458291f2351e9.jpeg","zoomable":true},{"id":"43120921985D4512806DE4AAB78926A0","url":"https://i5.walmartimages.com/asr/c99e86df-2749-4d7c-8b9c-4bafa346e28c.84f5299fee35f6a450bf881773cc8f02.jpeg","zoomable":true}],"thumbnailUrl":"https://i5.walmartimages.com/seo/Black-Rust-Oleum-Transformations-Semi-Gloss-Cabinet-Trim-Paint-372012-Quart_57833487-e596-49cb-99ac-4ef470723517.97b18685b4bc113446863a42ae96f8eb.jpeg"},"priceInfo":{"currentPrice":{"bestValue":null,"currencyUnit":"USD","price":19.97,"priceString":"$19.97","variantPriceString":"$19.97"},"isPriceReduced":false,"listPrice":null,"priceDisplayCodes":{"clearance":null,"eligibleForAssociateDiscount":true,"finalCostByWeight":null,"priceDisplayCondition":null,"reducedPrice":null,"rollback":null,"submapType":null},"priceReducedDisplay":null,"savingsAmount":null,"secondaryOfferBoost":null,"unitPrice":{"bestValue":false,"currencyUnit":"USD","price":0.624,"priceString":"62.4 ¢/fl oz","variantPriceString":null},"wasPrice":null},"productUrl":"/ip/Black-Rust-Oleum-Transformations-Semi-Gloss-Cabinet-Trim-Paint-372012-Quart/727839143","subscriptionEligible":false,"usItemId":"727839143","variants":["actual_color-black","count_per_pack-1","paint_finish-semi-gloss"]},"2WOXM1J0NL7M":{"availabilityStatus":"IN_STOCK","buyBoxSuppression":false,"discountPriceString":"","fulfillmentBadge":null,"id":"2WOXM1J0NL7M","imageInfo":{"allImages":[{"id":"92B05E2E300A468BB6AE85441BB53027","url":"https://i5.walmartimages.com/seo/Dark-Gray-Rust-Oleum-Transformations-Semi-Gloss-Cabinet-Trim-Paint-372010-Quart_f5abb7ab-2718-4e7a-b0c5-18f0894a7799.6f72598601d0d11ce0787e9d078366b9.jpeg","zoomable":true},{"id":"221C7A4511DA468C8E4AEF4D82108AC2","url":"https://i5.walmartimages.com/asr/fcdcdf54-ad7a-474b-a308-a1cad00812ad.9a9473749cb8686246c3e5c25e216365.jpeg","zoomable":true},{"id":"3C06D947C9064CADBFB7526038A0096A","url":"https://i5.walmartimages.com/asr/5f21c46d-4faf-4380-bfe4-f67f818da3cd.dbb654a0e883a43033da3585327500d1.jpeg","zoomable":false},{"id":"E9CCEF59621B4A4E8BDBCE24B3CBD313","url":"https://i5.walmartimages.com/asr/c6c2981c-be49-4c45-8078-3ea80732ee52.f7e841f3f27ce8b7e019f4f8f479b2dd.jpeg","zoomable":true},{"id":"43120921985D4512806DE4AAB78926A0","url":"https://i5.walmartimages.com/asr/c99e86df-2749-4d7c-8b9c-4bafa346e28c.84f5299fee35f6a450bf881773cc8f02.jpeg","zoomable":true}],"thumbnailUrl":"https://i5.walmartimages.com/seo/Dark-Gray-Rust-Oleum-Transformations-Semi-Gloss-Cabinet-Trim-Paint-372010-Quart_f5abb7ab-2718-4e7a-b0c5-18f0894a7799.6f72598601d0d11ce0787e9d078366b9.jpeg"},"priceInfo":{"capType":null,"comparisonPrice":null,"currentPrice":{"bestValue":null,"currencyUnit":"USD","price":19.97,"priceDisplay":"$19.97","priceString":"$19.97","variantPriceString":"$19.97"},"isPriceReduced":false,"listPrice":null,"priceDisplayCodes":{"clearance":null,"eligibleForAssociateDiscount":true,"finalCostByWeight":null,"priceDisplayCondition":null,"reducedPrice":null,"rollback":null,"submapType":null},"priceRange":{"currencyUnit":null,"denominations":null,"maxPrice":null,"minPrice":null,"priceString":null},"priceReducedDisplay":null,"savings":null,"savingsAmount":null,"secondaryOfferBoost":null,"shipPrice":null,"subscriptionPrice":null,"unitPrice":null,"wPlusEarlyAccessPrice":null,"walmartFundedAmount":null,"wasPrice":null},"productUrl":"/ip/Dark-Gray-Rust-Oleum-Transformations-Semi-Gloss-Cabinet-Trim-Paint-372010-Quart/685411720","subscriptionEligible":false,"usItemId":"685411720","variants":["actual_color-darkgray","count_per_pack-1","paint_finish-semi-gloss"]},"36A7S10D0KPJ":{"availabilityStatus":"IN_STOCK","buyBoxSuppression":false,"discountPriceString":"","fulfillmentBadge":null,"id":"36A7S10D0KPJ","imageInfo":{"allImages":[],"thumbnailUrl":null},"priceInfo":{"currentPrice":{"bestValue":null,"currencyUnit":"USD","price":46.27,"priceString":"$46.27","variantPriceString":"$46.27"},"isPriceReduced":false,"listPrice":null,"priceDisplayCodes":{"clearance":null,"eligibleForAssociateDiscount":true,"finalCostByWeight":null,"priceDisplayCondition":null,"reducedPrice":null,"rollback":null,"submapType":null},"priceReducedDisplay":null,"savingsAmount":null,"secondaryOfferBoost":null,"unitPrice":{"bestValue":true,"currencyUnit":"USD","price":1.45,"priceString":"$1.45/fl oz","variantPriceString":null},"wasPrice":null},"productUrl":"/ip/Dark-Gray-Rust-Oleum-Transformations-Semi-Gloss-Cabinet-Trim-Paint-Quart/378480229","subscriptionEligible":false,"usItemId":"378480229","variants":["actual_color-darkgray","count_per_pack-4","paint_finish-semi-gloss"]},"4EYNLLUXH0LF":{"availabilityStatus":"IN_STOCK","buyBoxSuppression":false,"discountPriceString":"","fulfillmentBadge":null,"id":"4EYNLLUXH0LF","imageInfo":{"allImages":[{"id":"832397CBF9D046BC9B40056CA7794C20","url":"https://i5.walmartimages.com/seo/Espresso-Rust-Oleum-Transformations-Semi-Gloss-Cabinet-Trim-Paint-372011-Quart_f66679bc-418c-46a8-89b5-6b11fa54f96f.00aed53a027c4faa6a557237413704b1.jpeg","zoomable":true},{"id":"63D2CC019CC44C13AAA113240385E56B","url":"https://i5.walmartimages.com/asr/baa4f639-50d3-4b2f-bc59-2f589f5f51bb.cee112d28d1305e55927c283fea0e7ec.jpeg","zoomable":true},{"id":"70DD250CE9324DDDB8A2C068E021AA02","url":"https://i5.walmartimages.com/asr/996334d6-1b04-4dbc-b291-cdc2a94980b2.2cec7644cf0b2c6fbbe70b1283d28fb7.jpeg","zoomable":false},{"id":"43120921985D4512806DE4AAB78926A0","url":"https://i5.walmartimages.com/asr/c99e86df-2749-4d7c-8b9c-4bafa346e28c.84f5299fee35f6a450bf881773cc8f02.jpeg","zoomable":true}],"thumbnailUrl":"https://i5.walmartimages.com/seo/Espresso-Rust-Oleum-Transformations-Semi-Gloss-Cabinet-Trim-Paint-372011-Quart_f66679bc-418c-46a8-89b5-6b11fa54f96f.00aed53a027c4faa6a557237413704b1.jpeg"},"priceInfo":{"currentPrice":{"bestValue":null,"currencyUnit":"USD","price":19.97,"priceString":"$19.97","variantPriceString":"$19.97"},"isPriceReduced":true,"listPrice":null,"priceDisplayCodes":{"clearance":null,"eligibleForAssociateDiscount":true,"finalCostByWeight":null,"priceDisplayCondition":null,"reducedPrice":null,"rollback":null,"submapType":null},"priceReducedDisplay":"Now $19.97","savingsAmount":null,"secondaryOfferBoost":null,"unitPrice":{"bestValue":false,"currencyUnit":"USD","price":0.624,"priceString":"62.4 ¢/fl oz","variantPriceString":null},"wasPrice":null},"productUrl":"/ip/Espresso-Rust-Oleum-Transformations-Semi-Gloss-Cabinet-Trim-Paint-372011-Quart/815263674","subscriptionEligible":false,"usItemId":"815263674","variants":["actual_color-espresso","count_per_pack-1","paint_finish-semi-gloss"]},"556ZYK1IYWMH":{"availabilityStatus":"IN_STOCK","buyBoxSuppression":false,"discountPriceString":"","fulfillmentBadge":null,"id":"556ZYK1IYWMH","imageInfo":{"allImages":[{"id":"FAA8B894575B4F9E867328A44F913132","url":"https://i5.walmartimages.com/seo/Cadet-Gray-Rust-Oleum-Transformations-Semi-Gloss-Cabinet-Trim-Paint-372009-Quart_2d2e513f-5936-4225-a4f2-779eb4100756.303d7372f45c07735fdb039d4d1fa7c6.jpeg","zoomable":true},{"id":"50821655A79A4A6C97AEB061DAAF63A2","url":"https://i5.walmartimages.com/asr/d1403741-20c0-4564-937b-a968dc0ad033.24228cad0ecea860c08e59fdc7119e9a.jpeg","zoomable":true},{"id":"8CFC02A63FA24057BF047D6CF5E12414","url":"https://i5.walmartimages.com/asr/d381bbd3-bd63-4410-8c32-e28eab346d2b.4871682e628f2011c6d3cadd215a124b.jpeg","zoomable":false},{"id":"F84B0D60B35F429FA6AC227CB73B18A3","url":"https://i5.walmartimages.com/asr/8527a403-4408-4248-b02d-abd5a0b25ad8.a1d88a31c2ae966553d62cce98b908e5.jpeg","zoomable":true},{"id":"43120921985D4512806DE4AAB78926A0","url":"https://i5.walmartimages.com/asr/c99e86df-2749-4d7c-8b9c-4bafa346e28c.84f5299fee35f6a450bf881773cc8f02.jpeg","zoomable":true}],"thumbnailUrl":"https://i5.walmartimages.com/seo/Cadet-Gray-Rust-Oleum-Transformations-Semi-Gloss-Cabinet-Trim-Paint-372009-Quart_2d2e513f-5936-4225-a4f2-779eb4100756.303d7372f45c07735fdb039d4d1fa7c6.jpeg"},"priceInfo":{"currentPrice":{"bestValue":null,"currencyUnit":"USD","price":19.97,"priceString":"$19.97","variantPriceString":"$19.97"},"isPriceReduced":true,"listPrice":null,"priceDisplayCodes":{"clearance":null,"eligibleForAssociateDiscount":true,"finalCostByWeight":null,"priceDisplayCondition":null,"reducedPrice":null,"rollback":null,"submapType":null},"priceReducedDisplay":"Now $19.97","savingsAmount":null,"secondaryOfferBoost":null,"unitPrice":null,"wasPrice":null},"productUrl":"/ip/Cadet-Gray-Rust-Oleum-Transformations-Semi-Gloss-Cabinet-Trim-Paint-372009-Quart/419121978","subscriptionEligible":false,"usItemId":"419121978","variants":["actual_color-cadetgray","count_per_pack-1","paint_finish-semi-gloss"]},"5R4S9HG6FKUD":{"availabilityStatus":"IN_STOCK","buyBoxSuppression":false,"discountPriceString":"","fulfillmentBadge":null,"id":"5R4S9HG6FKUD","imageInfo":{"allImages":[],"thumbnailUrl":null},"priceInfo":{"currentPrice":{"bestValue":null,"currencyUnit":"USD","price":46.27,"priceString":"$46.27","variantPriceString":"$46.27"},"isPriceReduced":false,"listPrice":null,"priceDisplayCodes":{"clearance":null,"eligibleForAssociateDiscount":true,"finalCostByWeight":null,"priceDisplayCondition":null,"reducedPrice":null,"rollback":null,"submapType":null},"priceReducedDisplay":null,"savingsAmount":null,"secondaryOfferBoost":null,"unitPrice":{"bestValue":false,"currencyUnit":"USD","price":1.45,"priceString":"$1.45/fl oz","variantPriceString":null},"wasPrice":null},"productUrl":"/ip/Pure-White-Rust-Oleum-Transformations-Semi-Gloss-Cabinet-Trim-Paint-Quart/257974597","subscriptionEligible":false,"usItemId":"257974597","variants":["actual_color-purewhite","count_per_pack-4","paint_finish-semi-gloss"]},"64LF3R8QOAKK":{"availabilityStatus":"IN_STOCK","buyBoxSuppression":false,"discountPriceString":"","fulfillmentBadge":null,"id":"64LF3R8QOAKK","imageInfo":{"allImages":[],"thumbnailUrl":null},"priceInfo":{"currentPrice":{"bestValue":null,"currencyUnit":"USD","price":46.27,"priceString":"$46.27","variantPriceString":"$46.27"},"isPriceReduced":false,"listPrice":null,"priceDisplayCodes":{"clearance":null,"eligibleForAssociateDiscount":true,"finalCostByWeight":null,"priceDisplayCondition":null,"reducedPrice":null,"rollback":null,"submapType":null},"priceReducedDisplay":null,"savingsAmount":null,"secondaryOfferBoost":null,"unitPrice":{"bestValue":false,"currencyUnit":"USD","price":1.45,"priceString":"$1.45/fl oz","variantPriceString":null},"wasPrice":null},"productUrl":"/ip/Black-Rust-Oleum-Transformations-Semi-Gloss-Cabinet-Trim-Paint-Quart/924966477","subscriptionEligible":false,"usItemId":"924966477","variants":["actual_color-black","count_per_pack-4","paint_finish-semi-gloss"]},"652S3L4JL02R":{"availabilityStatus":"IN_STOCK","buyBoxSuppression":false,"discountPriceString":"","fulfillmentBadge":"Tomorrow","id":"652S3L4JL02R","imageInfo":{"allImages":[{"id":"143ADFDD2E7B46428C9F41F7BF304AD7","url":"https://i5.walmartimages.com/seo/Pure-White-Rust-Oleum-Transformations-Semi-Gloss-Cabinet-Trim-Paint-372007-Quart_c0aa5415-1525-4f1e-920c-e821c1310363.3200cdccd233db40226ab53fba20dcb2.jpeg","zoomable":true},{"id":"D2EDBD9C09A2488EBA774865E75DA6D7","url":"https://i5.walmartimages.com/asr/3c7ad0d1-41c8-4510-89c3-5750ba6a2f33.860cb2167ee9c5e46cb64ed33e8741fd.jpeg","zoomable":false},{"id":"0DB1168DDB17440DAEED26D5DF980850","url":"https://i5.walmartimages.com/asr/685bcd78-63d1-4d6b-ad2d-c2d7e6e03b0a.6bc9c9e646ae3efdf4614f27ae4ec418.jpeg","zoomable":true},{"id":"6DF9666233664C38B954FACDCF90B2D8","url":"https://i5.walmartimages.com/asr/dfc24572-e1b8-41ea-a242-048121f3d0d7.1f9134a356105ad9c74bba289f4eab40.jpeg","zoomable":true},{"id":"43120921985D4512806DE4AAB78926A0","url":"https://i5.walmartimages.com/asr/c99e86df-2749-4d7c-8b9c-4bafa346e28c.84f5299fee35f6a450bf881773cc8f02.jpeg","zoomable":true}],"thumbnailUrl":"https://i5.walmartimages.com/seo/Pure-White-Rust-Oleum-Transformations-Semi-Gloss-Cabinet-Trim-Paint-372007-Quart_c0aa5415-1525-4f1e-920c-e821c1310363.3200cdccd233db40226ab53fba20dcb2.jpeg"},"priceInfo":{"currentPrice":{"bestValue":null,"currencyUnit":"USD","price":19.97,"priceString":"$19.97","variantPriceString":"$19.97"},"isPriceReduced":false,"listPrice":null,"priceDisplayCodes":{"clearance":null,"eligibleForAssociateDiscount":true,"finalCostByWeight":null,"priceDisplayCondition":null,"reducedPrice":null,"rollback":null,"submapType":null},"priceReducedDisplay":null,"savingsAmount":null,"secondaryOfferBoost":null,"unitPrice":null,"wasPrice":null},"productUrl":"/ip/Pure-White-Rust-Oleum-Transformations-Semi-Gloss-Cabinet-Trim-Paint-372007-Quart/360911364","subscriptionEligible":false,"usItemId":"360911364","variants":["actual_color-purewhite","count_per_pack-1","paint_finish-semi-gloss"]},"6Y420GWQDK12":{"availabilityStatus":"IN_STOCK","buyBoxSuppression":false,"discountPriceString":"","fulfillmentBadge":null,"id":"6Y420GWQDK12","imageInfo":{"allImages":[],"thumbnailUrl":null},"priceInfo":{"currentPrice":{"bestValue":null,"currencyUnit":"USD","price":46.27,"priceString":"$46.27","variantPriceString":"$46.27"},"isPriceReduced":true,"listPrice":null,"priceDisplayCodes":{"clearance":null,"eligibleForAssociateDiscount":true,"finalCostByWeight":null,"priceDisplayCondition":null,"reducedPrice":null,"rollback":null,"submapType":null},"priceReducedDisplay":"Now $46.27","savingsAmount":null,"secondaryOfferBoost":null,"unitPrice":{"bestValue":false,"currencyUnit":"USD","price":1.45,"priceString":"$1.45/fl oz","variantPriceString":null},"wasPrice":null},"productUrl":"/ip/Linen-Rust-Oleum-Transformations-Semi-Gloss-Cabinet-Trim-Paint-Quart/434282051","subscriptionEligible":false,"usItemId":"434282051","variants":["actual_color-linen","count_per_pack-4","paint_finish-semi-gloss"]}},"giftingEligibility":true,"shippingOption":{"availabilityStatus":"AVAILABLE","deliveryDate":"2023-12-17T22:59:00.000Z","internationalShipping":null,"maxDeliveryDate":null,"shipMethod":null,"shipPrice":null,"slaTier":"THREE_TO_FIVE_DAY"},"legalRestriction":false,"ironbankCategory":"Building Supply","catalogSellerId":0,"salesUnit":"EACH","fulfillmentType":"FC","petRx":{"eligible":false,"singleDispense":null},"averageRating":4.1,"pac":null,"badges":{"flags":null,"groups":[],"labels":null,"tags":[]},"showExploreOtherConditionsCTA":false,"variants":[],"hasHomeServices":null,"promoData":[],"conditionType":null,"imageInfo":{"allImages":[{"id":"92B05E2E300A468BB6AE85441BB53027","url":"https://i5.walmartimages.com/seo/Dark-Gray-Rust-Oleum-Transformations-Semi-Gloss-Cabinet-Trim-Paint-372010-Quart_f5abb7ab-2718-4e7a-b0c5-18f0894a7799.6f72598601d0d11ce0787e9d078366b9.jpeg","zoomable":true},{"id":"221C7A4511DA468C8E4AEF4D82108AC2","url":"https://i5.walmartimages.com/asr/fcdcdf54-ad7a-474b-a308-a1cad00812ad.9a9473749cb8686246c3e5c25e216365.jpeg","zoomable":true},{"id":"3C06D947C9064CADBFB7526038A0096A","url":"https://i5.walmartimages.com/asr/5f21c46d-4faf-4380-bfe4-f67f818da3cd.dbb654a0e883a43033da3585327500d1.jpeg","zoomable":false},{"id":"E9CCEF59621B4A4E8BDBCE24B3CBD313","url":"https://i5.walmartimages.com/asr/c6c2981c-be49-4c45-8078-3ea80732ee52.f7e841f3f27ce8b7e019f4f8f479b2dd.jpeg","zoomable":true},{"id":"43120921985D4512806DE4AAB78926A0","url":"https://i5.walmartimages.com/asr/c99e86df-2749-4d7c-8b9c-4bafa346e28c.84f5299fee35f6a450bf881773cc8f02.jpeg","zoomable":true}],"thumbnailUrl":"https://i5.walmartimages.com/seo/Dark-Gray-Rust-Oleum-Transformations-Semi-Gloss-Cabinet-Trim-Paint-372010-Quart_f5abb7ab-2718-4e7a-b0c5-18f0894a7799.6f72598601d0d11ce0787e9d078366b9.jpeg"},"tireLoadIndex":null,"productLocation":null,"checkStoreAvailabilityATC":false,"hasSellerBadge":null,"imageMap":{"0DB1168DDB17440DAEED26D5DF980850":{"id":"0DB1168DDB17440DAEED26D5DF980850","url":"https://i5.walmartimages.com/asr/685bcd78-63d1-4d6b-ad2d-c2d7e6e03b0a.6bc9c9e646ae3efdf4614f27ae4ec418.jpeg","zoomable":true},"143ADFDD2E7B46428C9F41F7BF304AD7":{"id":"143ADFDD2E7B46428C9F41F7BF304AD7","url":"https://i5.walmartimages.com/seo/Pure-White-Rust-Oleum-Transformations-Semi-Gloss-Cabinet-Trim-Paint-372007-Quart_c0aa5415-1525-4f1e-920c-e821c1310363.3200cdccd233db40226ab53fba20dcb2.jpeg","zoomable":true},"15B26A6DBB504F85B799B4BE1E25934C":{"id":"15B26A6DBB504F85B799B4BE1E25934C","url":"https://i5.walmartimages.com/asr/6191c2f3-7a81-4bf8-ae55-0d38486e0b96.feee5e2aef60f98df4049e83ec672abc.jpeg","zoomable":true},"20BB2374AFD846EEB7DD033869E67B8C":{"id":"20BB2374AFD846EEB7DD033869E67B8C","url":"https://i5.walmartimages.com/asr/3f8acfe5-8434-47fe-ad1c-82ffcf2a60d7.a552594bb9713bbdc14909e091f5e97c.jpeg","zoomable":false},"221C7A4511DA468C8E4AEF4D82108AC2":{"id":"221C7A4511DA468C8E4AEF4D82108AC2","url":"https://i5.walmartimages.com/asr/fcdcdf54-ad7a-474b-a308-a1cad00812ad.9a9473749cb8686246c3e5c25e216365.jpeg","zoomable":true},"3036D0E9F1D748A8B1F3B29A583D048B":{"id":"3036D0E9F1D748A8B1F3B29A583D048B","url":"https://i5.walmartimages.com/asr/ceabb1f2-592a-41f1-9fdd-c86a83367d84.1bcf5d4317edb6674466722aad5b373d.jpeg","zoomable":true},"3486004DAD284DE885965DC838FC8A84":{"id":"3486004DAD284DE885965DC838FC8A84","url":"https://i5.walmartimages.com/asr/86fd1340-761d-459a-8a5a-8b9c3b0dd72d.6a854095a371d4a7767783a90c2378b4.jpeg","zoomable":false},"39164D985D344EE5957623205B2FE23F":{"id":"39164D985D344EE5957623205B2FE23F","url":"https://i5.walmartimages.com/seo/Linen-Rust-Oleum-Transformations-Semi-Gloss-Cabinet-Trim-Paint-372008-Quart_58440b3c-0d5c-494a-ba83-164adad184e4.fa3204c110f4dc28144e04d4830a106e.jpeg","zoomable":true},"3C06D947C9064CADBFB7526038A0096A":{"id":"3C06D947C9064CADBFB7526038A0096A","url":"https://i5.walmartimages.com/asr/5f21c46d-4faf-4380-bfe4-f67f818da3cd.dbb654a0e883a43033da3585327500d1.jpeg","zoomable":false},"43120921985D4512806DE4AAB78926A0":{"id":"43120921985D4512806DE4AAB78926A0","url":"https://i5.walmartimages.com/asr/c99e86df-2749-4d7c-8b9c-4bafa346e28c.84f5299fee35f6a450bf881773cc8f02.jpeg","zoomable":true},"50821655A79A4A6C97AEB061DAAF63A2":{"id":"50821655A79A4A6C97AEB061DAAF63A2","url":"https://i5.walmartimages.com/asr/d1403741-20c0-4564-937b-a968dc0ad033.24228cad0ecea860c08e59fdc7119e9a.jpeg","zoomable":true},"63D2CC019CC44C13AAA113240385E56B":{"id":"63D2CC019CC44C13AAA113240385E56B","url":"https://i5.walmartimages.com/asr/baa4f639-50d3-4b2f-bc59-2f589f5f51bb.cee112d28d1305e55927c283fea0e7ec.jpeg","zoomable":true},"6DF9666233664C38B954FACDCF90B2D8":{"id":"6DF9666233664C38B954FACDCF90B2D8","url":"https://i5.walmartimages.com/asr/dfc24572-e1b8-41ea-a242-048121f3d0d7.1f9134a356105ad9c74bba289f4eab40.jpeg","zoomable":true},"70DD250CE9324DDDB8A2C068E021AA02":{"id":"70DD250CE9324DDDB8A2C068E021AA02","url":"https://i5.walmartimages.com/asr/996334d6-1b04-4dbc-b291-cdc2a94980b2.2cec7644cf0b2c6fbbe70b1283d28fb7.jpeg","zoomable":false},"832397CBF9D046BC9B40056CA7794C20":{"id":"832397CBF9D046BC9B40056CA7794C20","url":"https://i5.walmartimages.com/seo/Espresso-Rust-Oleum-Transformations-Semi-Gloss-Cabinet-Trim-Paint-372011-Quart_f66679bc-418c-46a8-89b5-6b11fa54f96f.00aed53a027c4faa6a557237413704b1.jpeg","zoomable":true},"84D18F41D73E4E329EA841A4FE986F35":{"id":"84D18F41D73E4E329EA841A4FE986F35","url":"https://i5.walmartimages.com/asr/8cce319f-70d9-41e5-91e3-76a77d1bc400.5229dce8223a6cd56bd87a10ff1dd8d0.jpeg","zoomable":true},"8CFC02A63FA24057BF047D6CF5E12414":{"id":"8CFC02A63FA24057BF047D6CF5E12414","url":"https://i5.walmartimages.com/asr/d381bbd3-bd63-4410-8c32-e28eab346d2b.4871682e628f2011c6d3cadd215a124b.jpeg","zoomable":false},"92B05E2E300A468BB6AE85441BB53027":{"id":"92B05E2E300A468BB6AE85441BB53027","url":"https://i5.walmartimages.com/seo/Dark-Gray-Rust-Oleum-Transformations-Semi-Gloss-Cabinet-Trim-Paint-372010-Quart_f5abb7ab-2718-4e7a-b0c5-18f0894a7799.6f72598601d0d11ce0787e9d078366b9.jpeg","zoomable":true},"C4FCBE7BF3E449D4AC90158024B54944":{"id":"C4FCBE7BF3E449D4AC90158024B54944","url":"https://i5.walmartimages.com/asr/fec90e3c-59e0-4742-8ce0-9e8389768886.1c99b920e4868c39531458291f2351e9.jpeg","zoomable":true},"CB46DABCEA454E7E9167AFE1A69AA339":{"id":"CB46DABCEA454E7E9167AFE1A69AA339","url":"https://i5.walmartimages.com/seo/Black-Rust-Oleum-Transformations-Semi-Gloss-Cabinet-Trim-Paint-372012-Quart_57833487-e596-49cb-99ac-4ef470723517.97b18685b4bc113446863a42ae96f8eb.jpeg","zoomable":true},"D2EDBD9C09A2488EBA774865E75DA6D7":{"id":"D2EDBD9C09A2488EBA774865E75DA6D7","url":"https://i5.walmartimages.com/asr/3c7ad0d1-41c8-4510-89c3-5750ba6a2f33.860cb2167ee9c5e46cb64ed33e8741fd.jpeg","zoomable":false},"E9CCEF59621B4A4E8BDBCE24B3CBD313":{"id":"E9CCEF59621B4A4E8BDBCE24B3CBD313","url":"https://i5.walmartimages.com/asr/c6c2981c-be49-4c45-8078-3ea80732ee52.f7e841f3f27ce8b7e019f4f8f479b2dd.jpeg","zoomable":true},"F84B0D60B35F429FA6AC227CB73B18A3":{"id":"F84B0D60B35F429FA6AC227CB73B18A3","url":"https://i5.walmartimages.com/asr/8527a403-4408-4248-b02d-abd5a0b25ad8.a1d88a31c2ae966553d62cce98b908e5.jpeg","zoomable":true},"FAA8B894575B4F9E867328A44F913132":{"id":"FAA8B894575B4F9E867328A44F913132","url":"https://i5.walmartimages.com/seo/Cadet-Gray-Rust-Oleum-Transformations-Semi-Gloss-Cabinet-Trim-Paint-372009-Quart_2d2e513f-5936-4225-a4f2-779eb4100756.303d7372f45c07735fdb039d4d1fa7c6.jpeg","zoomable":true}},"newConditionProductId":null,"upc":"020066495992","redirect":{"replacedByItemId":"","replacedByProductId":"","replacedByProductUrlText":""},"shippingRestriction":false,"availabilityStatus":"IN_STOCK","blitzItem":null,"promoDiscount":null,"rewards":null,"associatedBundleId":null,"orderLimit":59,"numberOfReviews":149,"isPreowned":false,"buyNowEligible":true,"semStoreData":null,"canonicalUrl":"/ip/Dark-Gray-Rust-Oleum-Transformations-Semi-Gloss-Cabinet-Trim-Paint-372010-Quart/685411720","groupMetaData":null,"name":"Dark Gray, Rust-Oleum Transformations Semi-Gloss Cabinet & Trim Paint-372010, Quart","fulfillmentOptions":[{"__typename":"ShippingOptionV2","availabilityStatus":"IN_STOCK","availableQuantity":59,"intent":true,"inventoryStatus":null,"locationText":"Laurel, 20723","maxOrderQuantity":99,"orderLimit":59,"restricted":false,"selected":false,"speedDetails":{"deliveryDate":"2023-12-17T22:59:00.000Z","freeFulfillment":false,"fulfillmentBadge":null,"fulfillmentPrice":null,"wPlusEligible":false},"subscriptionSubmessage":"NONE","type":"SHIPPING"},{"__typename":"PickupOptionV2","availabilityStatus":"OUT_OF_STOCK","availableQuantity":null,"checkStoreAvailability":true,"intent":false,"inventoryStatus":null,"locationText":"Laurel Supercenter","maxOrderQuantity":null,"orderLimit":null,"productLocation":null,"selected":false,"speedDetails":null,"storeName":null,"subscriptionSubmessage":"NONE","type":"PICKUP"},{"__typename":"DeliveryOptionV2","availabilityStatus":"NOT_AVAILABLE","availableQuantity":null,"intent":false,"locationText":"Laurel, 20723","maxOrderQuantity":null,"orderLimit":null,"selected":false,"speedDetails":null,"subscriptionSubmessage":"NONE","type":"DELIVERY"}],"sellerId":"F55CDC31AB754BB68FE0B39041159D63","shipAsIs":false}